<?xml version="1.0" encoding="UTF-8"?>
<odoo>
    <record id="movie_action" model="ir.actions.act_window">
        <field name="name">Movies</field>
        <field name="res_model">movie.movie</field>
        <field name="view_mode">tree,form</field>
        <field name="help" type="html">
            <p class="o_view_nocontent_smiling_face">
                Create a new Movie, the first step of a new movie!
            </p>
        </field>
    </record>
    <record id="movie_type_action" model="ir.actions.act_window">
        <field name="name">movie types </field>
        <field name="res_model">movie.type</field>
        <field name="view_mode">tree,form</field>
        <field name="help" type="html">
            <p class="o_view_nocontent_smiling_face">
                 Create a new Type, the first step of a new type!
            </p>
        </field>
    </record>

    <record id="movie_language_action" model="ir.actions.act_window">
        <field name="name">movie languages</field>
        <field name="res_model">movie.languages</field>
        <field name="view_mode">tree,form</field>
        <field name="help" type="html">
            <p class="o_view_nocontent_smiling_face">
                 Create a new Language, the first step of a new movie!
            </p>
        </field>
    </record>

    <record id="movie_show_action" model="ir.actions.act_window">
        <field name="name">movie show</field>
        <field name="res_model">movie.show</field>
        <field name="view_mode">tree,form</field>
        <field name="domain">[('movie_id', '=', active_id)]</field>
        <field name="help" type="html">
            <p class="o_view_nocontent_smiling_face">
                 Create a new Language, the first step of a new movie!
            </p>
        </field>
    </record>
    <record id="movie_seating_template_action" model="ir.actions.act_window">
        <field name="name">Seating template</field>
        <field name="res_model">movie.seating.template</field>
        <field name="view_mode">tree,form</field>       
        <field name="help" type="html">
            <p class="o_view_nocontent_smiling_face">
                 Create a new Screen, the first step of a new movie!
            </p>
        </field>

    </record>

    <record id="movie_seating_arrangement_action" model="ir.actions.act_window">
        <field name="name">Seating arrangement</field>
        <field name="res_model">movie.seat.arrangement</field>
        <field name="view_mode">tree,form</field>
         <!-- <field name="domain">[('movie_id', '=', active_id)]</field> -->
        <!-- <field name="domain">[('seat_template_id', '=', active_id)]</field> -->
        <field name="help" type="html">
            <p class="o_view_nocontent_smiling_face">
                 Create a new Screen, the first step of a new movie!
            </p>
        </field>

    </record>

</odoo>
